loadbalancer_interface/__init__.py
loadbalancer_interface/base.py
loadbalancer_interface/provides.py
loadbalancer_interface/pytest_plugin.py
loadbalancer_interface/requires.py
loadbalancer_interface/examples/lb-consumer/charmcraft.yaml
loadbalancer_interface/examples/lb-consumer/config.yaml
loadbalancer_interface/examples/lb-consumer/metadata.yaml
loadbalancer_interface/examples/lb-consumer/requirements.txt
loadbalancer_interface/examples/lb-consumer/src/charm.py
loadbalancer_interface/examples/lb-consumer-reactive/config.yaml
loadbalancer_interface/examples/lb-consumer-reactive/layer.yaml
loadbalancer_interface/examples/lb-consumer-reactive/metadata.yaml
loadbalancer_interface/examples/lb-consumer-reactive/wheelhouse.txt
loadbalancer_interface/examples/lb-consumer-reactive/reactive/charm.py
loadbalancer_interface/examples/lb-provider/charmcraft.yaml
loadbalancer_interface/examples/lb-provider/metadata.yaml
loadbalancer_interface/examples/lb-provider/requirements.txt
loadbalancer_interface/examples/lb-provider/src/charm.py
loadbalancer_interface/examples/lb-provider-reactive/layer.yaml
loadbalancer_interface/examples/lb-provider-reactive/metadata.yaml
loadbalancer_interface/examples/lb-provider-reactive/wheelhouse.txt
loadbalancer_interface/examples/lb-provider-reactive/lib/charms/layer/provides_reactive.py
loadbalancer_interface/examples/lb-provider-reactive/reactive/charm.py
loadbalancer_interface/schemas/__init__.py
loadbalancer_interface/schemas/base.py
loadbalancer_interface/schemas/v1.py
loadbalancer_interface-1.2.1.dist-info/licenses/LICENSE
loadbalancer_interface-1.2.1.dist-info/METADATA
loadbalancer_interface-1.2.1.dist-info/WHEEL
loadbalancer_interface-1.2.1.dist-info/entry_points.txt
loadbalancer_interface-1.2.1.dist-info/top_level.txt
loadbalancer_interface-1.2.1.dist-info/RECORD
