Metadata-Version: 2.4
Name: loadbalancer_interface
Version: 1.2.1
Summary: 'loadbalancer' interface protocol API library
Home-page: https://github.com/juju-solutions/loadbalancer-interface
Author: Cory Johns
Author-email: cory.johns@canonical.com
License: Apache License 2.0
License-File: LICENSE
Requires-Dist: ops>=1.0.0
Requires-Dist: cached_property
Requires-Dist: marshmallow<4.0.0
Requires-Dist: marshmallow-enum
Requires-Dist: ops_reactive_interface
Dynamic: author
Dynamic: author-email
Dynamic: description
Dynamic: description-content-type
Dynamic: home-page
Dynamic: license
Dynamic: license-file
Dynamic: requires-dist
Dynamic: summary
